logwatchdog/__init__.py
logwatchdog/email_service.py
logwatchdog/log_config.ini
logwatchdog/log_monitor.py
logwatchdog/main.py
logwatchdog/notifier.py
logwatchdog/tray_notifier.py
logwatchdog/cli/__init__.py
logwatchdog/cli/main.py
logwatchdog/gui/__init__.py
logwatchdog/gui/main.py
logwatchdog-1.0.2.dist-info/licenses/LICENSE
logwatchdog-1.0.2.dist-info/METADATA
logwatchdog-1.0.2.dist-info/WHEEL
logwatchdog-1.0.2.dist-info/entry_points.txt
logwatchdog-1.0.2.dist-info/top_level.txt
logwatchdog-1.0.2.dist-info/RECORD
