Metadata-Version: 2.4
Name: logwatchdog
Version: 1.0.2
Summary: Comprehensive Windows log monitoring and management solution
Home-page: https://github.com/pandiyarajk/logwatchdog
Download-URL: https://github.com/pandiyarajk/logwatchdog/releases
Author: Pandiyaraj Karuppasamy
Author-email: pandiyarajk@live.com
License: MIT
Project-URL: Bug Reports, https://github.com/pandiyarajk/logwatchdog/issues
Project-URL: Source, https://github.com/pandiyarajk/logwatchdog
Project-URL: Documentation, https://github.com/pandiyarajk/logwatchdog/blob/main/README.md
Project-URL: Changelog, https://github.com/pandiyarajk/logwatchdog/blob/main/CHANGELOG.md
Project-URL: Download, https://github.com/pandiyarajk/logwatchdog/releases
Keywords: log,monitoring,windows,notifications,alerts,system-administration,security,auditing,real-time,watchdog,monitoring-tool,log-analysis,event-logging,system-monitoring
Platform: win32
Platform: win_amd64
Classifier: Development Status :: 5 - Production/Stable
Classifier: Intended Audience :: Developers
Classifier: Intended Audience :: System Administrators
Classifier: Intended Audience :: Information Technology
Classifier: License :: OSI Approved :: MIT License
Classifier: Operating System :: Microsoft :: Windows :: Windows 10
Classifier: Operating System :: Microsoft :: Windows :: Windows 11
Classifier: Operating System :: Microsoft :: Windows
Classifier: Programming Language :: Python :: 3
Classifier: Programming Language :: Python :: 3.7
Classifier: Programming Language :: Python :: 3.8
Classifier: Programming Language :: Python :: 3.9
Classifier: Programming Language :: Python :: 3.10
Classifier: Programming Language :: Python :: 3.11
Classifier: Programming Language :: Python :: 3.12
Classifier: Programming Language :: Python :: 3.13
Classifier: Topic :: System :: Logging
Classifier: Topic :: System :: Monitoring
Classifier: Topic :: System :: Networking :: Monitoring
Classifier: Topic :: Utilities
Classifier: Topic :: System :: Systems Administration
Classifier: Topic :: Security
Classifier: Topic :: Software Development :: Libraries :: Python Modules
Classifier: Topic :: Software Development :: Libraries :: Application Frameworks
Requires-Python: >=3.7
License-File: LICENSE
Requires-Dist: plyer>=2.0.0
Requires-Dist: python-dotenv>=0.19.0
Requires-Dist: psutil>=5.8.0
Requires-Dist: watchdog>=2.1.0
Requires-Dist: email-validator>=1.1.3
Requires-Dist: pyinstaller>=5.0.0
Provides-Extra: dev
Requires-Dist: pytest>=6.0.0; extra == "dev"
Requires-Dist: pytest-cov>=2.10.0; extra == "dev"
Requires-Dist: black>=21.0.0; extra == "dev"
Requires-Dist: flake8>=3.8.0; extra == "dev"
Requires-Dist: mypy>=0.800; extra == "dev"
Requires-Dist: pre-commit>=2.15.0; extra == "dev"
Requires-Dist: tox>=3.20.0; extra == "dev"
Requires-Dist: sphinx>=4.0.0; extra == "dev"
Requires-Dist: sphinx-rtd-theme>=0.5.0; extra == "dev"
Provides-Extra: test
Requires-Dist: pytest>=6.0.0; extra == "test"
Requires-Dist: pytest-cov>=2.10.0; extra == "test"
Provides-Extra: docs
Requires-Dist: sphinx>=4.0.0; extra == "docs"
Requires-Dist: sphinx-rtd-theme>=0.5.0; extra == "docs"
Dynamic: author
Dynamic: author-email
Dynamic: classifier
Dynamic: description
Dynamic: description-content-type
Dynamic: download-url
Dynamic: home-page
Dynamic: keywords
Dynamic: license
Dynamic: license-file
Dynamic: platform
Dynamic: project-url
Dynamic: provides-extra
Dynamic: requires-dist
Dynamic: requires-python
Dynamic: summary
